pbfe/__init__.py
pbfe-0.0.1.dist-info/LICENSE
pbfe-0.0.1.dist-info/METADATA
pbfe-0.0.1.dist-info/WHEEL
pbfe-0.0.1.dist-info/top_level.txt
pbfe-0.0.1.dist-info/RECORD
